NanoLeafDiscovery/__init__.py
NanoLeafDiscovery/nano.py
NanoLeafDiscovery-0.1.0.dist-info/LICENCE.txt
NanoLeafDiscovery-0.1.0.dist-info/METADATA
NanoLeafDiscovery-0.1.0.dist-info/WHEEL
NanoLeafDiscovery-0.1.0.dist-info/top_level.txt
NanoLeafDiscovery-0.1.0.dist-info/RECORD
