Metadata-Version: 2.1
Name: NanoLeafDiscovery
Version: 0.1.0
Summary: Discovery module for nanoleaf
Home-page: https://github.com/NotBlue-Dev/NanoLeaf-Discovery
Author: NotBlue
Author-email: 
License: MIT
Keywords: nanoleaf
Platform: UNKNOWN
Classifier: Development Status :: 5 - Production/Stable
Classifier: Intended Audience :: Education
Classifier: Operating System :: Microsoft :: Windows :: Windows 10
Classifier: License :: OSI Approved :: MIT License
Classifier: Programming Language :: Python :: 3
Requires-Dist: requests
